color_differences_analyzer/__init__.py
color_differences_analyzer/__main__.py
color_differences_analyzer/main.py
color_differences_analyzer-0.2.0.dist-info/entry_points.txt
color_differences_analyzer-0.2.0.dist-info/LICENSE
color_differences_analyzer-0.2.0.dist-info/WHEEL
color_differences_analyzer-0.2.0.dist-info/METADATA
color_differences_analyzer-0.2.0.dist-info/RECORD
