Metadata-Version: 2.1
Name: color-differences-analyzer
Version: 0.2.0
Summary: Command line interface to analyze differences of colors from images implemented with Python.
Home-page: https://github.com/leynier/color-differences-analyzer
License: MIT
Author: Leynier Gutiérrez González
Author-email: leynier41@gmail.com
Requires-Python: >=3.8,<4.0
Classifier: License :: OSI Approved :: MIT License
Classifier: Programming Language :: Python :: 3
Classifier: Programming Language :: Python :: 3.8
Classifier: Programming Language :: Python :: 3.9
Requires-Dist: colormath (>=3.0.0,<4.0.0)
Requires-Dist: matplotlib (>=3.4.2,<4.0.0)
Requires-Dist: numpy (>=1.20.3,<2.0.0)
Requires-Dist: openpyxl (>=3.0.7,<4.0.0)
Requires-Dist: pandas (>=1.2.4,<2.0.0)
Requires-Dist: scikit-image (>=0.18.1,<0.19.0)
Requires-Dist: typer (>=0.3.2,<0.4.0)
Project-URL: Documentation, https://github.com/leynier/color-differences-analyzer
Project-URL: Repository, https://github.com/leynier/color-differences-analyzer
